{
	"info": {
		"_postman_id": "2c8c9713-0cd4-48b3-bc6e-b0dcf2474eab",
		"name": "New Collection",
		"schema": "https://schema.getpostman.com/json/collection/v2.1.0/collection.json",
		"_exporter_id": "15190701"
	},
	"item": [
		{
			"name": "https://jsonplaceholder.typicode.com/",
			"item": [
				{
					"name": "todos",
					"request": {
						"method": "GET",
						"header": [],
						"url": {
							"raw": "https://jsonplaceholder.typicode.com/todos",
							"protocol": "https",
							"host": [
								"jsonplaceholder",
								"typicode",
								"com"
							],
							"path": [
								"todos"
							]
						}
					},
					"response": []
				},
				{
					"name": "posts",
					"protocolProfileBehavior": {
						"disableBodyPruning": true
					},
					"request": {
						"method": "GET",
						"header": [],
						"body": {
							"mode": "raw",
							"raw": "",
							"options": {
								"raw": {
									"language": "json"
								}
							}
						},
						"url": {
							"raw": "https://jsonplaceholder.typicode.com/posts",
							"protocol": "https",
							"host": [
								"jsonplaceholder",
								"typicode",
								"com"
							],
							"path": [
								"posts"
							]
						}
					},
					"response": []
				},
				{
					"name": "posts",
					"request": {
						"method": "POST",
						"header": [],
						"body": {
							"mode": "raw",
							"raw": "{\r\n    \"title\": \"title_AlextTest01\",\r\n    \"body\": \"body_AlextTest01\",\r\n    \"userId\": 1001\r\n  }",
							"options": {
								"raw": {
									"language": "json"
								}
							}
						},
						"url": {
							"raw": "https://jsonplaceholder.typicode.com/posts",
							"protocol": "https",
							"host": [
								"jsonplaceholder",
								"typicode",
								"com"
							],
							"path": [
								"posts"
							]
						}
					},
					"response": []
				},
				{
					"name": "posts/(id)",
					"request": {
						"method": "GET",
						"header": [],
						"url": {
							"raw": "https://jsonplaceholder.typicode.com/posts/1001",
							"protocol": "https",
							"host": [
								"jsonplaceholder",
								"typicode",
								"com"
							],
							"path": [
								"posts",
								"1001"
							]
						}
					},
					"response": []
				},
				{
					"name": "posts/1/comments",
					"request": {
						"method": "GET",
						"header": [],
						"url": {
							"raw": "https://jsonplaceholder.typicode.com/posts/1/comments",
							"protocol": "https",
							"host": [
								"jsonplaceholder",
								"typicode",
								"com"
							],
							"path": [
								"posts",
								"1",
								"comments"
							]
						}
					},
					"response": []
				},
				{
					"name": "/comments?postId=1",
					"request": {
						"method": "GET",
						"header": [],
						"url": {
							"raw": "https://jsonplaceholder.typicode.com/comments?postId=1",
							"protocol": "https",
							"host": [
								"jsonplaceholder",
								"typicode",
								"com"
							],
							"path": [
								"comments"
							],
							"query": [
								{
									"key": "postId",
									"value": "1"
								}
							]
						}
					},
					"response": []
				},
				{
					"name": "comments",
					"request": {
						"method": "GET",
						"header": [],
						"url": {
							"raw": "https://jsonplaceholder.typicode.com/comments",
							"protocol": "https",
							"host": [
								"jsonplaceholder",
								"typicode",
								"com"
							],
							"path": [
								"comments"
							]
						}
					},
					"response": []
				},
				{
					"name": "albums",
					"request": {
						"method": "GET",
						"header": [],
						"url": {
							"raw": "https://jsonplaceholder.typicode.com/albums",
							"protocol": "https",
							"host": [
								"jsonplaceholder",
								"typicode",
								"com"
							],
							"path": [
								"albums"
							]
						}
					},
					"response": []
				},
				{
					"name": "photos",
					"request": {
						"method": "GET",
						"header": [],
						"url": {
							"raw": "https://jsonplaceholder.typicode.com/photos",
							"protocol": "https",
							"host": [
								"jsonplaceholder",
								"typicode",
								"com"
							],
							"path": [
								"photos"
							]
						}
					},
					"response": []
				},
				{
					"name": "users",
					"request": {
						"method": "GET",
						"header": [],
						"url": {
							"raw": "https://jsonplaceholder.typicode.com/users",
							"protocol": "https",
							"host": [
								"jsonplaceholder",
								"typicode",
								"com"
							],
							"path": [
								"users"
							]
						}
					},
					"response": []
				}
			]
		},
		{
			"name": "https://dummy.restapiexample.com/api/v1/",
			"item": [
				{
					"name": "employees",
					"request": {
						"method": "GET",
						"header": [],
						"url": {
							"raw": "https://dummy.restapiexample.com/api/v1/employees",
							"protocol": "https",
							"host": [
								"dummy",
								"restapiexample",
								"com"
							],
							"path": [
								"api",
								"v1",
								"employees"
							]
						}
					},
					"response": []
				},
				{
					"name": "employee/(id)",
					"request": {
						"method": "GET",
						"header": [],
						"url": {
							"raw": "https://dummy.restapiexample.com/api/v1/employee/9861",
							"protocol": "https",
							"host": [
								"dummy",
								"restapiexample",
								"com"
							],
							"path": [
								"api",
								"v1",
								"employee",
								"9861"
							]
						}
					},
					"response": []
				},
				{
					"name": "create",
					"request": {
						"method": "POST",
						"header": [],
						"body": {
							"mode": "raw",
							"raw": "{\"name\":\"test2\",\"salary\":\"1234\",\"age\":\"23\"}",
							"options": {
								"raw": {
									"language": "json"
								}
							}
						},
						"url": {
							"raw": "https://dummy.restapiexample.com/api/v1/create",
							"protocol": "https",
							"host": [
								"dummy",
								"restapiexample",
								"com"
							],
							"path": [
								"api",
								"v1",
								"create"
							]
						}
					},
					"response": []
				}
			]
		},
		{
			"name": "Mocks",
			"item": [
				{
					"name": "Mock from pycharm",
					"event": [
						{
							"listen": "test",
							"script": {
								"exec": [
									"pm.test(\"Status code is 200\", function () {\r",
									"    pm.response.to.have.status(200);\r",
									"});\r",
									"pm.test(\"Body matches string\", function () {\r",
									"    pm.expect(pm.response.text()).to.include(\"simple text\");\r",
									"});\r",
									"\r",
									"pm.test(\"Just a simple\", function () {\r",
									"    var jsonData = pm.response.json();\r",
									"    pm.expect(jsonData.code).to.eql(1);\r",
									"});\r",
									""
								],
								"type": "text/javascript"
							}
						}
					],
					"request": {
						"method": "GET",
						"header": [],
						"url": {
							"raw": "http://127.0.0.1:5000/json",
							"protocol": "http",
							"host": [
								"127",
								"0",
								"0",
								"1"
							],
							"port": "5000",
							"path": [
								"json"
							]
						}
					},
					"response": []
				}
			]
		},
		{
			"name": "https://dummyjson.com/",
			"item": [
				{
					"name": "products",
					"request": {
						"method": "GET",
						"header": [],
						"url": {
							"raw": "https://dummyjson.com/products",
							"protocol": "https",
							"host": [
								"dummyjson",
								"com"
							],
							"path": [
								"products"
							]
						}
					},
					"response": []
				},
				{
					"name": "products/(id)",
					"request": {
						"method": "GET",
						"header": [],
						"url": {
							"raw": "https://dummyjson.com/products/2",
							"protocol": "https",
							"host": [
								"dummyjson",
								"com"
							],
							"path": [
								"products",
								"2"
							]
						}
					},
					"response": []
				},
				{
					"name": "search?q=(search_title_string))",
					"request": {
						"method": "GET",
						"header": [],
						"url": {
							"raw": "https://dummyjson.com/products/search?q=phone",
							"protocol": "https",
							"host": [
								"dummyjson",
								"com"
							],
							"path": [
								"products",
								"search"
							],
							"query": [
								{
									"key": "q",
									"value": "phone"
								}
							]
						}
					},
					"response": []
				},
				{
					"name": "products/add",
					"request": {
						"method": "POST",
						"header": [],
						"body": {
							"mode": "raw",
							"raw": "{\r\n    \"title\": \"BMW Pencil\"\r\n    }",
							"options": {
								"raw": {
									"language": "json"
								}
							}
						},
						"url": {
							"raw": "https://dummyjson.com/products/add",
							"protocol": "https",
							"host": [
								"dummyjson",
								"com"
							],
							"path": [
								"products",
								"add"
							]
						}
					},
					"response": []
				},
				{
					"name": "limit=(int_val)&skip=(int_val)&select=title,price",
					"request": {
						"method": "GET",
						"header": [],
						"url": {
							"raw": "https://dummyjson.com/products?limit=10&skip=3&select=brand,title,price",
							"protocol": "https",
							"host": [
								"dummyjson",
								"com"
							],
							"path": [
								"products"
							],
							"query": [
								{
									"key": "limit",
									"value": "10"
								},
								{
									"key": "skip",
									"value": "3"
								},
								{
									"key": "select",
									"value": "brand,title,price"
								}
							]
						}
					},
					"response": []
				},
				{
					"name": "categories",
					"request": {
						"method": "GET",
						"header": [],
						"url": {
							"raw": "https://dummyjson.com/products/categories",
							"protocol": "https",
							"host": [
								"dummyjson",
								"com"
							],
							"path": [
								"products",
								"categories"
							]
						}
					},
					"response": []
				},
				{
					"name": "https://dummyjson.com/products/category/smartphones",
					"request": {
						"method": "GET",
						"header": []
					},
					"response": []
				},
				{
					"name": "category/smartphones",
					"request": {
						"method": "GET",
						"header": []
					},
					"response": []
				},
				{
					"name": "products/1",
					"request": {
						"method": "PUT",
						"header": [],
						"url": {
							"raw": "https://dummyjson.com/products/1",
							"protocol": "https",
							"host": [
								"dummyjson",
								"com"
							],
							"path": [
								"products",
								"1"
							]
						}
					},
					"response": []
				},
				{
					"name": "products/1",
					"request": {
						"method": "DELETE",
						"header": [],
						"url": {
							"raw": "https://dummyjson.com/products/1",
							"protocol": "https",
							"host": [
								"dummyjson",
								"com"
							],
							"path": [
								"products",
								"1"
							]
						}
					},
					"response": []
				}
			]
		},
		{
			"name": "SOAP",
			"item": [
				{
					"name": "tempconvert",
					"protocolProfileBehavior": {
						"disableBodyPruning": true
					},
					"request": {
						"method": "GET",
						"header": [],
						"body": {
							"mode": "raw",
							"raw": "",
							"options": {
								"raw": {
									"language": "xml"
								}
							}
						},
						"url": {
							"raw": "https://www.w3schools.com/xml/tempconvert.asmx",
							"protocol": "https",
							"host": [
								"www",
								"w3schools",
								"com"
							],
							"path": [
								"xml",
								"tempconvert.asmx"
							]
						}
					},
					"response": []
				},
				{
					"name": "CountryInfoService",
					"protocolProfileBehavior": {
						"disableBodyPruning": true
					},
					"request": {
						"method": "GET",
						"header": [
							{
								"key": "Content-Type",
								"value": "text/xml; charset=utf-8",
								"type": "text"
							}
						],
						"body": {
							"mode": "raw",
							"raw": "<?xml version=\\\"1.0\\\" encoding=\\\"utf-8\\\"?>\r\n            <soap:Envelope xmlns:soap=\\\"http://schemas.xmlsoap.org/soap/envelope/\\\">\r\n                <soap:Body>\r\n                    <CountryIntPhoneCode xmlns=\\\"http://www.oorsprong.org/websamples.countryinfo\\\">\r\n                        <sCountryISOCode>IN</sCountryISOCode>\r\n                    </CountryIntPhoneCode>\r\n                </soap:Body>\r\n            </soap:Envelope>",
							"options": {
								"raw": {
									"language": "xml"
								}
							}
						},
						"url": {
							"raw": "http://webservices.oorsprong.org/websamples.countryinfo/CountryInfoService.wso",
							"protocol": "http",
							"host": [
								"webservices",
								"oorsprong",
								"org"
							],
							"path": [
								"websamples.countryinfo",
								"CountryInfoService.wso"
							]
						}
					},
					"response": []
				}
			]
		}
	]
}